hogBGR/HOG.py
hogBGR/HOGvisualized.py
hogBGR/SampleCode.py
hogBGR/__init__.py
hogBGR/util.py
hogBGR-0.0.1.dist-info/LICENSE
hogBGR-0.0.1.dist-info/METADATA
hogBGR-0.0.1.dist-info/WHEEL
hogBGR-0.0.1.dist-info/top_level.txt
hogBGR-0.0.1.dist-info/RECORD
